flaterra/__init__.py
flaterra/__main__.py
flaterra/version.py
flaterra-0.1.7.dist-info/METADATA
flaterra-0.1.7.dist-info/WHEEL
flaterra-0.1.7.dist-info/entry_points.txt
flaterra-0.1.7.dist-info/top_level.txt
flaterra-0.1.7.dist-info/RECORD
