Metadata-Version: 2.1
Name: flaterra
Version: 0.1.7
Summary: UNKNOWN
Home-page: UNKNOWN
Author: Daniel Luca
Author-email: daniel.luca@consensys.net
License: MIT
Platform: UNKNOWN
